[{"file_id": "PXL_20210314_020719504.MP.jpg", "file_path": "/Users/lana/DataClass/SpaceCleaner/Resources/temp_img/PXL_20210314_020719504.MP.jpg", "file_bytes_size": 6936661, "Date": "2021:03:13", "Time": "18:07:19", "madeBy": "Google", "model": "Pixel 4 XL", "coordinates": []}, {"file_id": "IMG_0006.jpg", "file_path": "/Users/lana/DataClass/SpaceCleaner/Resources/temp_img/IMG_0006.jpg", "file_bytes_size": 1171723, "Date": "2021:03:14", "Time": "18:04:16", "madeBy": "Apple", "model": "iPhone 12 Pro", "coordinates": ["37.70803055555555", "-121.87331388888889"]}, {"file_id": "IMG_0005.jpg", "file_path": "/Users/lana/DataClass/SpaceCleaner/Resources/temp_img/IMG_0005.jpg", "file_bytes_size": 1112899, "Date": "2021:03:14", "Time": "18:04:15", "madeBy": "Apple", "model": "iPhone 12 Pro", "coordinates": ["37.70802777777778", "-121.87331388888889"]}, {"file_id": "IMG_0004.jpg", "file_path": "/Users/lana/DataClass/SpaceCleaner/Resources/temp_img/IMG_0004.jpg", "file_bytes_size": 1441448, "Date": "2021:03:14", "Time": "18:04:09", "madeBy": "Apple", "model": "iPhone 12 Pro", "coordinates": ["37.70803333333333", "-121.87330555555556"]}, {"file_id": "296A7765.jpg", "file_path": "/Users/lana/DataClass/SpaceCleaner/Resources/temp_img/296A7765.jpg", "file_bytes_size": 1730073, "Date": "2019:08:18", "Time": "21:45:44", "madeBy": "Canon", "model": "Canon EOS 5D Mark III", "coordinates": []}, {"file_id": "IMG_0004_copy.jpg", "file_path": "/Users/lana/DataClass/SpaceCleaner/Resources/temp_img/IMG_0004_copy.jpg", "file_bytes_size": 1441448, "Date": "2021:03:14", "Time": "18:04:09", "madeBy": "Apple", "model": "iPhone 12 Pro", "coordinates": ["37.70803333333333", "-121.87330555555556"]}, {"file_id": "PXL_20210314_020726755.MP.jpg", "file_path": "/Users/lana/DataClass/SpaceCleaner/Resources/temp_img/PXL_20210314_020726755.MP.jpg", "file_bytes_size": 10055933, "Date": "2021:03:13", "Time": "18:07:26", "madeBy": "Google", "model": "Pixel 4 XL", "coordinates": []}, {"file_id": "IMG_0035.jpg", "file_path": "/Users/lana/DataClass/SpaceCleaner/Resources/temp_img/IMG_0035.jpg", "file_bytes_size": 4087081, "Date": "2021:03:20", "Time": "19:01:49", "madeBy": "Apple", "model": "iPhone 12 Pro", "coordinates": ["37.707655555555554", "-121.87329166666666"]}, {"file_id": "IMG_0034.jpg", "file_path": "/Users/lana/DataClass/SpaceCleaner/Resources/temp_img/IMG_0034.jpg", "file_bytes_size": 3976181, "Date": "2021:03:20", "Time": "19:01:45", "madeBy": "Apple", "model": "iPhone 12 Pro", "coordinates": ["37.70765277777778", "-121.87329166666666"]}, {"file_id": "PXL_20210314_020732248.MP.jpg", "file_path": "/Users/lana/DataClass/SpaceCleaner/Resources/temp_img/PXL_20210314_020732248.MP.jpg", "file_bytes_size": 7004654, "Date": "2021:03:13", "Time": "18:07:32", "madeBy": "Google", "model": "Pixel 4 XL", "coordinates": []}, {"file_id": "IMG_0033.jpg", "file_path": "/Users/lana/DataClass/SpaceCleaner/Resources/temp_img/IMG_0033.jpg", "file_bytes_size": 3433641, "Date": "2021:03:20", "Time": "19:01:42", "madeBy": "Apple", "model": "iPhone 12 Pro", "coordinates": ["37.70766944444444", "-121.87326944444445"]}, {"file_id": "IMG_0032.jpg", "file_path": "/Users/lana/DataClass/SpaceCleaner/Resources/temp_img/IMG_0032.jpg", "file_bytes_size": 3450306, "Date": "2021:03:20", "Time": "17:11:56", "madeBy": "Apple", "model": "iPhone 12 Pro", "coordinates": []}, {"file_id": "IMG_0030.jpg", "file_path": "/Users/lana/DataClass/SpaceCleaner/Resources/temp_img/IMG_0030.jpg", "file_bytes_size": 3971345, "Date": "2021:03:20", "Time": "17:11:54", "madeBy": "Apple", "model": "iPhone 12 Pro", "coordinates": []}, {"file_id": "IMG_0031.jpg", "file_path": "/Users/lana/DataClass/SpaceCleaner/Resources/temp_img/IMG_0031.jpg", "file_bytes_size": 3943706, "Date": "2021:03:20", "Time": "17:11:54", "madeBy": "Apple", "model": "iPhone 12 Pro", "coordinates": []}]